vspsum/__init__.py
vspsum/sum.py
vspsum-0.2.dist-info/METADATA
vspsum-0.2.dist-info/WHEEL
vspsum-0.2.dist-info/top_level.txt
vspsum-0.2.dist-info/RECORD
