Metadata-Version: 2.1
Name: vspsum
Version: 0.2
Summary: A simple Python package for summing two numbers
Home-page: https://github.com/vishnusureshperumbavoor/vspsum
Author: Vishnu Suresh Perumbavoor
Author-email: vishnusureshperumbavoor@gmail.com
